sri_check-1.13.1.dist-info/licenses/LICENSE
sricheck/__init__.py
sricheck/__main__.py
sricheck/sricheck.py
sri_check-1.13.1.dist-info/METADATA
sri_check-1.13.1.dist-info/WHEEL
sri_check-1.13.1.dist-info/entry_points.txt
sri_check-1.13.1.dist-info/top_level.txt
sri_check-1.13.1.dist-info/RECORD
