Metadata-Version: 2.4
Name: sri-check
Version: 1.13.1
Summary: Subresource Integrity Checker
Author-email: Marc Wickenden <code@4armed.com>
Project-URL: Homepage, https://github.com/4armed/sri-check
Requires-Python: >=3.6
License-File: LICENSE
Requires-Dist: beautifulsoup4>=4.0
Requires-Dist: blinker==1.7.0
Requires-Dist: lxml>=4.8
Requires-Dist: requests>=2.0
Requires-Dist: selenium>=4.25
Dynamic: license-file
